binboy/__init__.py
binboy/__main__.py
binboy-0.1.0.dist-info/LICENSE
binboy-0.1.0.dist-info/METADATA
binboy-0.1.0.dist-info/WHEEL
binboy-0.1.0.dist-info/entry_points.txt
binboy-0.1.0.dist-info/top_level.txt
binboy-0.1.0.dist-info/RECORD
