Metadata-Version: 2.1
Name: binboy
Version: 0.1.0
Summary: A beautiful binary code printer
Home-page: https://github.com/AitzazImtiaz/Bin-Boy
Author: AitzazImtiaz
Author-email: aitzazimtiaz855@gmail.com
Classifier: Programming Language :: Python :: 3
Classifier: License :: OSI Approved :: MIT License
Classifier: Operating System :: OS Independent
License-File: LICENSE
